QYtool/__init__.py
QYtool/datatool.py
QYtool/dirtool.py
QYtool/mathtool.py
QYtool/nntool.py
QYtool/progressbar.py
QYtool/timer.py
QYtool/wandblog.py
qytool-1.0.8.dist-info/METADATA
qytool-1.0.8.dist-info/WHEEL
qytool-1.0.8.dist-info/licenses/LICENSE
qytool-1.0.8.dist-info/RECORD
