Metadata-Version: 2.3
Name: QYtool
Version: 1.0.8
Summary: My own toolbox for research projects.
Project-URL: Homepage, https://github.com/QiYuan-Zhang
Project-URL: Website, https://qiyuan-zhang.github.io
Author-email: Xuewen Zhang <xuewen.zhang741@outlook.com>
Maintainer-email: Xuewen Zhang <xuewen.zhang741@outlook.com>
License:                                 Apache License
License-File: LICENSE
Keywords: tool
Classifier: Development Status :: 4 - Beta
Classifier: Intended Audience :: Developers
Classifier: License :: OSI Approved :: Apache Software License
Classifier: Programming Language :: Python :: 3
Classifier: Programming Language :: Python :: 3.6
Classifier: Programming Language :: Python :: 3.7
Classifier: Programming Language :: Python :: 3.8
Classifier: Programming Language :: Python :: 3.9
Classifier: Topic :: Software Development :: Build Tools
Requires-Python: >=3.6
Requires-Dist: casadi>3.0.0
Requires-Dist: numpy
Requires-Dist: rich
Requires-Dist: torch
Requires-Dist: wandb
